fr_youssef_test/__init__.py
fr_youssef_test-2.0.2.dist-info/METADATA
fr_youssef_test-2.0.2.dist-info/WHEEL
fr_youssef_test-2.0.2.dist-info/top_level.txt
fr_youssef_test-2.0.2.dist-info/RECORD
