Metadata-Version: 2.2
Name: fr_youssef_test
Version: 2.0.2
Summary: A short description of your package
Author-email: youssef <y.hamila@cfp.energy>
Classifier: Programming Language :: Python :: 3
Classifier: License :: OSI Approved :: MIT License
Classifier: Operating System :: OS Independent
Requires-Python: >=3.7
Requires-Dist: requests
Requires-Dist: numpy
